{
  "id": "65d5f98f-fcd4-46b0-8f36-b0ba7a703b63",
  "prevId": "00000000-0000-0000-0000-000000000000",
  "version": "7",
  "dialect": "postgresql",
  "tables": {
    "public.book_reviews": {
      "name": "book_reviews",
      "schema": "",
      "columns": {
        "id": {
          "name": "id",
          "type": "serial",
          "primaryKey": true,
          "notNull": true
        },
        "book_id": {
          "name": "book_id",
          "type": "integer",
          "primaryKey": false,
          "notNull": true
        },
        "visitor_id": {
          "name": "visitor_id",
          "type": "text",
          "primaryKey": false,
          "notNull": true
        },
        "display_name": {
          "name": "display_name",
          "type": "text",
          "primaryKey": false,
          "notNull": true
        },
        "rating": {
          "name": "rating",
          "type": "integer",
          "primaryKey": false,
          "notNull": true
        },
        "comment": {
          "name": "comment",
          "type": "text",
          "primaryKey": false,
          "notNull": false
        },
        "created_at": {
          "name": "created_at",
          "type": "timestamp",
          "primaryKey": false,
          "notNull": true,
          "default": "now()"
        }
      },
      "indexes": {},
      "foreignKeys": {
        "book_reviews_book_id_books_id_fk": {
          "name": "book_reviews_book_id_books_id_fk",
          "tableFrom": "book_reviews",
          "tableTo": "books",
          "columnsFrom": [
            "book_id"
          ],
          "columnsTo": [
            "id"
          ],
          "onDelete": "no action",
          "onUpdate": "no action"
        }
      },
      "compositePrimaryKeys": {},
      "uniqueConstraints": {},
      "policies": {},
      "checkConstraints": {},
      "isRLSEnabled": false
    },
    "public.books": {
      "name": "books",
      "schema": "",
      "columns": {
        "id": {
          "name": "id",
          "type": "serial",
          "primaryKey": true,
          "notNull": true
        },
        "title": {
          "name": "title",
          "type": "text",
          "primaryKey": false,
          "notNull": true
        },
        "author": {
          "name": "author",
          "type": "text",
          "primaryKey": false,
          "notNull": true
        },
        "genre": {
          "name": "genre",
          "type": "text",
          "primaryKey": false,
          "notNull": true
        },
        "category": {
          "name": "category",
          "type": "text",
          "primaryKey": false,
          "notNull": true
        },
        "price": {
          "name": "price",
          "type": "numeric(10, 2)",
          "primaryKey": false,
          "notNull": true
        },
        "rating": {
          "name": "rating",
          "type": "numeric(3, 2)",
          "primaryKey": false,
          "notNull": false,
          "default": "'4.5'"
        },
        "cover_url": {
          "name": "cover_url",
          "type": "text",
          "primaryKey": false,
          "notNull": true
        },
        "description": {
          "name": "description",
          "type": "text",
          "primaryKey": false,
          "notNull": false
        },
        "visible": {
          "name": "visible",
          "type": "boolean",
          "primaryKey": false,
          "notNull": true,
          "default": true
        },
        "created_at": {
          "name": "created_at",
          "type": "timestamp",
          "primaryKey": false,
          "notNull": true,
          "default": "now()"
        }
      },
      "indexes": {},
      "foreignKeys": {},
      "compositePrimaryKeys": {},
      "uniqueConstraints": {},
      "policies": {},
      "checkConstraints": {},
      "isRLSEnabled": false
    },
    "public.conversations": {
      "name": "conversations",
      "schema": "",
      "columns": {
        "id": {
          "name": "id",
          "type": "serial",
          "primaryKey": true,
          "notNull": true
        },
        "title": {
          "name": "title",
          "type": "text",
          "primaryKey": false,
          "notNull": true
        },
        "created_at": {
          "name": "created_at",
          "type": "timestamp",
          "primaryKey": false,
          "notNull": true,
          "default": "now()"
        }
      },
      "indexes": {},
      "foreignKeys": {},
      "compositePrimaryKeys": {},
      "uniqueConstraints": {},
      "policies": {},
      "checkConstraints": {},
      "isRLSEnabled": false
    },
    "public.dismissed_duplicates": {
      "name": "dismissed_duplicates",
      "schema": "",
      "columns": {
        "id": {
          "name": "id",
          "type": "serial",
          "primaryKey": true,
          "notNull": true
        },
        "book_id_a": {
          "name": "book_id_a",
          "type": "integer",
          "primaryKey": false,
          "notNull": true
        },
        "book_id_b": {
          "name": "book_id_b",
          "type": "integer",
          "primaryKey": false,
          "notNull": true
        },
        "created_at": {
          "name": "created_at",
          "type": "timestamp",
          "primaryKey": false,
          "notNull": true,
          "default": "now()"
        }
      },
      "indexes": {},
      "foreignKeys": {},
      "compositePrimaryKeys": {},
      "uniqueConstraints": {},
      "policies": {},
      "checkConstraints": {},
      "isRLSEnabled": false
    },
    "public.draft_ebooks": {
      "name": "draft_ebooks",
      "schema": "",
      "columns": {
        "id": {
          "name": "id",
          "type": "serial",
          "primaryKey": true,
          "notNull": true
        },
        "title": {
          "name": "title",
          "type": "text",
          "primaryKey": false,
          "notNull": true
        },
        "genre": {
          "name": "genre",
          "type": "text",
          "primaryKey": false,
          "notNull": true
        },
        "topic": {
          "name": "topic",
          "type": "text",
          "primaryKey": false,
          "notNull": true
        },
        "description": {
          "name": "description",
          "type": "text",
          "primaryKey": false,
          "notNull": false
        },
        "outline": {
          "name": "outline",
          "type": "text",
          "primaryKey": false,
          "notNull": false
        },
        "content": {
          "name": "content",
          "type": "text",
          "primaryKey": false,
          "notNull": false
        },
        "cover_url": {
          "name": "cover_url",
          "type": "text",
          "primaryKey": false,
          "notNull": false
        },
        "background_url": {
          "name": "background_url",
          "type": "text",
          "primaryKey": false,
          "notNull": false
        },
        "pdf_url": {
          "name": "pdf_url",
          "type": "text",
          "primaryKey": false,
          "notNull": false
        },
        "suggested_price": {
          "name": "suggested_price",
          "type": "numeric(10, 2)",
          "primaryKey": false,
          "notNull": false
        },
        "status": {
          "name": "status",
          "type": "text",
          "primaryKey": false,
          "notNull": true,
          "default": "'pending'"
        },
        "cover_style_id": {
          "name": "cover_style_id",
          "type": "text",
          "primaryKey": false,
          "notNull": false
        },
        "overlay_approved": {
          "name": "overlay_approved",
          "type": "boolean",
          "primaryKey": false,
          "notNull": false,
          "default": false
        },
        "created_at": {
          "name": "created_at",
          "type": "timestamp",
          "primaryKey": false,
          "notNull": true,
          "default": "now()"
        },
        "published_at": {
          "name": "published_at",
          "type": "timestamp",
          "primaryKey": false,
          "notNull": false
        }
      },
      "indexes": {},
      "foreignKeys": {},
      "compositePrimaryKeys": {},
      "uniqueConstraints": {},
      "policies": {},
      "checkConstraints": {},
      "isRLSEnabled": false
    },
    "public.generation_jobs": {
      "name": "generation_jobs",
      "schema": "",
      "columns": {
        "id": {
          "name": "id",
          "type": "serial",
          "primaryKey": true,
          "notNull": true
        },
        "type": {
          "name": "type",
          "type": "text",
          "primaryKey": false,
          "notNull": true
        },
        "genre": {
          "name": "genre",
          "type": "text",
          "primaryKey": false,
          "notNull": true
        },
        "status": {
          "name": "status",
          "type": "text",
          "primaryKey": false,
          "notNull": true,
          "default": "'queued'"
        },
        "total_items": {
          "name": "total_items",
          "type": "integer",
          "primaryKey": false,
          "notNull": false,
          "default": 0
        },
        "completed_items": {
          "name": "completed_items",
          "type": "integer",
          "primaryKey": false,
          "notNull": false,
          "default": 0
        },
        "error": {
          "name": "error",
          "type": "text",
          "primaryKey": false,
          "notNull": false
        },
        "topics": {
          "name": "topics",
          "type": "text[]",
          "primaryKey": false,
          "notNull": false
        },
        "last_activity_at": {
          "name": "last_activity_at",
          "type": "timestamp",
          "primaryKey": false,
          "notNull": false
        },
        "created_at": {
          "name": "created_at",
          "type": "timestamp",
          "primaryKey": false,
          "notNull": true,
          "default": "now()"
        },
        "started_at": {
          "name": "started_at",
          "type": "timestamp",
          "primaryKey": false,
          "notNull": false
        },
        "completed_at": {
          "name": "completed_at",
          "type": "timestamp",
          "primaryKey": false,
          "notNull": false
        }
      },
      "indexes": {},
      "foreignKeys": {},
      "compositePrimaryKeys": {},
      "uniqueConstraints": {},
      "policies": {},
      "checkConstraints": {},
      "isRLSEnabled": false
    },
    "public.messages": {
      "name": "messages",
      "schema": "",
      "columns": {
        "id": {
          "name": "id",
          "type": "serial",
          "primaryKey": true,
          "notNull": true
        },
        "conversation_id": {
          "name": "conversation_id",
          "type": "integer",
          "primaryKey": false,
          "notNull": true
        },
        "role": {
          "name": "role",
          "type": "text",
          "primaryKey": false,
          "notNull": true
        },
        "content": {
          "name": "content",
          "type": "text",
          "primaryKey": false,
          "notNull": true
        },
        "created_at": {
          "name": "created_at",
          "type": "timestamp",
          "primaryKey": false,
          "notNull": true,
          "default": "now()"
        }
      },
      "indexes": {},
      "foreignKeys": {
        "messages_conversation_id_conversations_id_fk": {
          "name": "messages_conversation_id_conversations_id_fk",
          "tableFrom": "messages",
          "tableTo": "conversations",
          "columnsFrom": [
            "conversation_id"
          ],
          "columnsTo": [
            "id"
          ],
          "onDelete": "cascade",
          "onUpdate": "no action"
        }
      },
      "compositePrimaryKeys": {},
      "uniqueConstraints": {},
      "policies": {},
      "checkConstraints": {},
      "isRLSEnabled": false
    },
    "public.order_items": {
      "name": "order_items",
      "schema": "",
      "columns": {
        "id": {
          "name": "id",
          "type": "serial",
          "primaryKey": true,
          "notNull": true
        },
        "order_id": {
          "name": "order_id",
          "type": "integer",
          "primaryKey": false,
          "notNull": true
        },
        "book_id": {
          "name": "book_id",
          "type": "integer",
          "primaryKey": false,
          "notNull": true
        },
        "price": {
          "name": "price",
          "type": "numeric(10, 2)",
          "primaryKey": false,
          "notNull": true
        },
        "title": {
          "name": "title",
          "type": "text",
          "primaryKey": false,
          "notNull": true
        },
        "purchase_type": {
          "name": "purchase_type",
          "type": "text",
          "primaryKey": false,
          "notNull": false,
          "default": "'download'"
        }
      },
      "indexes": {},
      "foreignKeys": {
        "order_items_order_id_orders_id_fk": {
          "name": "order_items_order_id_orders_id_fk",
          "tableFrom": "order_items",
          "tableTo": "orders",
          "columnsFrom": [
            "order_id"
          ],
          "columnsTo": [
            "id"
          ],
          "onDelete": "no action",
          "onUpdate": "no action"
        },
        "order_items_book_id_books_id_fk": {
          "name": "order_items_book_id_books_id_fk",
          "tableFrom": "order_items",
          "tableTo": "books",
          "columnsFrom": [
            "book_id"
          ],
          "columnsTo": [
            "id"
          ],
          "onDelete": "no action",
          "onUpdate": "no action"
        }
      },
      "compositePrimaryKeys": {},
      "uniqueConstraints": {},
      "policies": {},
      "checkConstraints": {},
      "isRLSEnabled": false
    },
    "public.orders": {
      "name": "orders",
      "schema": "",
      "columns": {
        "id": {
          "name": "id",
          "type": "serial",
          "primaryKey": true,
          "notNull": true
        },
        "customer_email": {
          "name": "customer_email",
          "type": "text",
          "primaryKey": false,
          "notNull": true
        },
        "stripe_session_id": {
          "name": "stripe_session_id",
          "type": "text",
          "primaryKey": false,
          "notNull": false
        },
        "stripe_payment_intent_id": {
          "name": "stripe_payment_intent_id",
          "type": "text",
          "primaryKey": false,
          "notNull": false
        },
        "status": {
          "name": "status",
          "type": "text",
          "primaryKey": false,
          "notNull": true,
          "default": "'pending'"
        },
        "total": {
          "name": "total",
          "type": "numeric(10, 2)",
          "primaryKey": false,
          "notNull": true
        },
        "created_at": {
          "name": "created_at",
          "type": "timestamp",
          "primaryKey": false,
          "notNull": true,
          "default": "now()"
        }
      },
      "indexes": {},
      "foreignKeys": {},
      "compositePrimaryKeys": {},
      "uniqueConstraints": {
        "orders_stripe_session_id_unique": {
          "name": "orders_stripe_session_id_unique",
          "nullsNotDistinct": false,
          "columns": [
            "stripe_session_id"
          ]
        }
      },
      "policies": {},
      "checkConstraints": {},
      "isRLSEnabled": false
    },
    "public.reading_access": {
      "name": "reading_access",
      "schema": "",
      "columns": {
        "id": {
          "name": "id",
          "type": "serial",
          "primaryKey": true,
          "notNull": true
        },
        "book_id": {
          "name": "book_id",
          "type": "integer",
          "primaryKey": false,
          "notNull": true
        },
        "customer_email": {
          "name": "customer_email",
          "type": "text",
          "primaryKey": false,
          "notNull": true
        },
        "stripe_session_id": {
          "name": "stripe_session_id",
          "type": "text",
          "primaryKey": false,
          "notNull": false
        },
        "expires_at": {
          "name": "expires_at",
          "type": "timestamp",
          "primaryKey": false,
          "notNull": true
        },
        "created_at": {
          "name": "created_at",
          "type": "timestamp",
          "primaryKey": false,
          "notNull": true,
          "default": "now()"
        }
      },
      "indexes": {},
      "foreignKeys": {
        "reading_access_book_id_books_id_fk": {
          "name": "reading_access_book_id_books_id_fk",
          "tableFrom": "reading_access",
          "tableTo": "books",
          "columnsFrom": [
            "book_id"
          ],
          "columnsTo": [
            "id"
          ],
          "onDelete": "no action",
          "onUpdate": "no action"
        }
      },
      "compositePrimaryKeys": {},
      "uniqueConstraints": {},
      "policies": {},
      "checkConstraints": {},
      "isRLSEnabled": false
    },
    "public.subscription_events": {
      "name": "subscription_events",
      "schema": "",
      "columns": {
        "id": {
          "name": "id",
          "type": "serial",
          "primaryKey": true,
          "notNull": true
        },
        "event_type": {
          "name": "event_type",
          "type": "text",
          "primaryKey": false,
          "notNull": true
        },
        "customer_email": {
          "name": "customer_email",
          "type": "text",
          "primaryKey": false,
          "notNull": false
        },
        "plan_id": {
          "name": "plan_id",
          "type": "integer",
          "primaryKey": false,
          "notNull": false
        },
        "subscription_id": {
          "name": "subscription_id",
          "type": "integer",
          "primaryKey": false,
          "notNull": false
        },
        "metadata": {
          "name": "metadata",
          "type": "text",
          "primaryKey": false,
          "notNull": false
        },
        "created_at": {
          "name": "created_at",
          "type": "timestamp",
          "primaryKey": false,
          "notNull": true,
          "default": "now()"
        }
      },
      "indexes": {},
      "foreignKeys": {},
      "compositePrimaryKeys": {},
      "uniqueConstraints": {},
      "policies": {},
      "checkConstraints": {},
      "isRLSEnabled": false
    },
    "public.subscription_plans": {
      "name": "subscription_plans",
      "schema": "",
      "columns": {
        "id": {
          "name": "id",
          "type": "serial",
          "primaryKey": true,
          "notNull": true
        },
        "name": {
          "name": "name",
          "type": "text",
          "primaryKey": false,
          "notNull": true
        },
        "tier": {
          "name": "tier",
          "type": "text",
          "primaryKey": false,
          "notNull": true
        },
        "monthly_price": {
          "name": "monthly_price",
          "type": "numeric(10, 2)",
          "primaryKey": false,
          "notNull": true
        },
        "reads_per_month": {
          "name": "reads_per_month",
          "type": "integer",
          "primaryKey": false,
          "notNull": true
        },
        "downloads_per_month": {
          "name": "downloads_per_month",
          "type": "integer",
          "primaryKey": false,
          "notNull": true,
          "default": 0
        },
        "stripe_price_id": {
          "name": "stripe_price_id",
          "type": "text",
          "primaryKey": false,
          "notNull": false
        },
        "stripe_product_id": {
          "name": "stripe_product_id",
          "type": "text",
          "primaryKey": false,
          "notNull": false
        },
        "is_active": {
          "name": "is_active",
          "type": "boolean",
          "primaryKey": false,
          "notNull": false,
          "default": true
        },
        "created_at": {
          "name": "created_at",
          "type": "timestamp",
          "primaryKey": false,
          "notNull": true,
          "default": "now()"
        }
      },
      "indexes": {},
      "foreignKeys": {},
      "compositePrimaryKeys": {},
      "uniqueConstraints": {},
      "policies": {},
      "checkConstraints": {},
      "isRLSEnabled": false
    },
    "public.subscription_usage": {
      "name": "subscription_usage",
      "schema": "",
      "columns": {
        "id": {
          "name": "id",
          "type": "serial",
          "primaryKey": true,
          "notNull": true
        },
        "subscription_id": {
          "name": "subscription_id",
          "type": "integer",
          "primaryKey": false,
          "notNull": true
        },
        "book_id": {
          "name": "book_id",
          "type": "integer",
          "primaryKey": false,
          "notNull": true
        },
        "usage_type": {
          "name": "usage_type",
          "type": "text",
          "primaryKey": false,
          "notNull": true
        },
        "period_start": {
          "name": "period_start",
          "type": "timestamp",
          "primaryKey": false,
          "notNull": true
        },
        "period_end": {
          "name": "period_end",
          "type": "timestamp",
          "primaryKey": false,
          "notNull": true
        },
        "created_at": {
          "name": "created_at",
          "type": "timestamp",
          "primaryKey": false,
          "notNull": true,
          "default": "now()"
        }
      },
      "indexes": {},
      "foreignKeys": {
        "subscription_usage_subscription_id_subscriptions_id_fk": {
          "name": "subscription_usage_subscription_id_subscriptions_id_fk",
          "tableFrom": "subscription_usage",
          "tableTo": "subscriptions",
          "columnsFrom": [
            "subscription_id"
          ],
          "columnsTo": [
            "id"
          ],
          "onDelete": "no action",
          "onUpdate": "no action"
        },
        "subscription_usage_book_id_books_id_fk": {
          "name": "subscription_usage_book_id_books_id_fk",
          "tableFrom": "subscription_usage",
          "tableTo": "books",
          "columnsFrom": [
            "book_id"
          ],
          "columnsTo": [
            "id"
          ],
          "onDelete": "no action",
          "onUpdate": "no action"
        }
      },
      "compositePrimaryKeys": {},
      "uniqueConstraints": {},
      "policies": {},
      "checkConstraints": {},
      "isRLSEnabled": false
    },
    "public.subscriptions": {
      "name": "subscriptions",
      "schema": "",
      "columns": {
        "id": {
          "name": "id",
          "type": "serial",
          "primaryKey": true,
          "notNull": true
        },
        "customer_email": {
          "name": "customer_email",
          "type": "text",
          "primaryKey": false,
          "notNull": true
        },
        "plan_id": {
          "name": "plan_id",
          "type": "integer",
          "primaryKey": false,
          "notNull": true
        },
        "stripe_subscription_id": {
          "name": "stripe_subscription_id",
          "type": "text",
          "primaryKey": false,
          "notNull": false
        },
        "stripe_customer_id": {
          "name": "stripe_customer_id",
          "type": "text",
          "primaryKey": false,
          "notNull": false
        },
        "status": {
          "name": "status",
          "type": "text",
          "primaryKey": false,
          "notNull": true,
          "default": "'active'"
        },
        "current_period_start": {
          "name": "current_period_start",
          "type": "timestamp",
          "primaryKey": false,
          "notNull": false
        },
        "current_period_end": {
          "name": "current_period_end",
          "type": "timestamp",
          "primaryKey": false,
          "notNull": false
        },
        "cancelled_at": {
          "name": "cancelled_at",
          "type": "timestamp",
          "primaryKey": false,
          "notNull": false
        },
        "created_at": {
          "name": "created_at",
          "type": "timestamp",
          "primaryKey": false,
          "notNull": true,
          "default": "now()"
        }
      },
      "indexes": {},
      "foreignKeys": {
        "subscriptions_plan_id_subscription_plans_id_fk": {
          "name": "subscriptions_plan_id_subscription_plans_id_fk",
          "tableFrom": "subscriptions",
          "tableTo": "subscription_plans",
          "columnsFrom": [
            "plan_id"
          ],
          "columnsTo": [
            "id"
          ],
          "onDelete": "no action",
          "onUpdate": "no action"
        }
      },
      "compositePrimaryKeys": {},
      "uniqueConstraints": {},
      "policies": {},
      "checkConstraints": {},
      "isRLSEnabled": false
    },
    "public.users": {
      "name": "users",
      "schema": "",
      "columns": {
        "id": {
          "name": "id",
          "type": "varchar",
          "primaryKey": true,
          "notNull": true,
          "default": "gen_random_uuid()"
        },
        "username": {
          "name": "username",
          "type": "text",
          "primaryKey": false,
          "notNull": true
        },
        "password": {
          "name": "password",
          "type": "text",
          "primaryKey": false,
          "notNull": true
        }
      },
      "indexes": {},
      "foreignKeys": {},
      "compositePrimaryKeys": {},
      "uniqueConstraints": {
        "users_username_unique": {
          "name": "users_username_unique",
          "nullsNotDistinct": false,
          "columns": [
            "username"
          ]
        }
      },
      "policies": {},
      "checkConstraints": {},
      "isRLSEnabled": false
    }
  },
  "enums": {},
  "schemas": {},
  "sequences": {},
  "roles": {},
  "policies": {},
  "views": {},
  "_meta": {
    "columns": {},
    "schemas": {},
    "tables": {}
  }
}